pyMorseTranslator/__init__.py
pyMorseTranslator/character.py
pyMorseTranslator/translator.py
pyMorseTranslator/test/__init__.py
pyMorseTranslator-1.2.0.dist-info/LICENSE
pyMorseTranslator-1.2.0.dist-info/METADATA
pyMorseTranslator-1.2.0.dist-info/WHEEL
pyMorseTranslator-1.2.0.dist-info/top_level.txt
pyMorseTranslator-1.2.0.dist-info/RECORD
