Metadata-Version: 2.1
Name: pyMorseTranslator
Version: 1.2.0
Summary: A library for decoding and encoding strings in Morse code.
Home-page: https://github.com/Eagle-Eye2324/pyMorseTranslator
Author: Robbie Munro
Author-email: rmunro2324@gmail.com
License: GPL-3.0-only
Platform: UNKNOWN
